README.md
setup.py
kea3/__init__.py
kea3/cli.py
kea3/kmeta.py
kea3/models.py
kea3/util.py
kea3.egg-info/PKG-INFO
kea3.egg-info/SOURCES.txt
kea3.egg-info/dependency_links.txt
kea3.egg-info/entry_points.txt
kea3.egg-info/requires.txt
kea3.egg-info/top_level.txt
kea3/etc/_kea.config
kea3/etc/plugin.config
kea3/plugin/__init__.py
kea3/plugin/db.py
kea3/plugin/fsconfig.py
kea3/plugin/metadata.py
kea3/plugin/stats.py
kea3/plugin/transaction.py
kea3/plugin/lt_storage/__init__.py
test/test_file_metadata.py
test/test_test.py
web/__init__.py