Metadata-Version: 1.1
Name: kea3
Version: 0.1.8
Summary: file metadata tracker
Home-page: https://gitlab.com/mf42/kea3
Author: Mark Fiers
Author-email: mark.fiers.42@gmail.com
License: UNKNOWN
Platform: UNKNOWN
Classifier: Development Status :: 4 - Beta
Classifier: Environment :: Console
Classifier: Operating System :: OS Independent
Classifier: Programming Language :: Python
Classifier: Programming Language :: Python :: 3
Classifier: Programming Language :: Python :: 3.6
Classifier: Programming Language :: Python :: 3.7
